aitrika/__init__.py
aitrika/app.py
aitrika/data/__init__.py
aitrika/data/breast_cancer_brca1_brca2.pdf
aitrika/data/review_of_breast_cancer_pathological_image_processing.pdf
aitrika/data/targets_of_neuroprotection_in_glaucoma.pdf
aitrika/engine/__init__.py
aitrika/engine/aitrika.py
aitrika/llm/__init__.py
aitrika/llm/anyscale.py
aitrika/llm/base_llm.py
aitrika/llm/groq.py
aitrika/llm/huggingface.py
aitrika/llm/neutrino.py
aitrika/llm/ollama.py
aitrika/llm/openai.py
aitrika/main.py
aitrika/prompts/__init__.py
aitrika/prompts/prompts.py
aitrika/utils/__init__.py
aitrika/utils/load_spacy_model.py
aitrika/utils/loader.py
aitrika/utils/text_parser.py
aitrika-0.3.5.3.dist-info/LICENSE
aitrika-0.3.5.3.dist-info/METADATA
aitrika-0.3.5.3.dist-info/WHEEL
aitrika-0.3.5.3.dist-info/RECORD
