Metadata-Version: 2.1
Name: aitrika
Version: 0.3.5.3
Summary: Enhance your knowledge in medical research.
License: MIT
Author: Danilo Palumbo
Requires-Python: >=3.10,<4.0
Classifier: License :: OSI Approved :: MIT License
Classifier: Programming Language :: Python :: 3
Classifier: Programming Language :: Python :: 3.10
Classifier: Programming Language :: Python :: 3.11
Classifier: Programming Language :: Python :: 3.12
Requires-Dist: bio (>=1.7.0,<2.0.0)
Requires-Dist: llama-index (>=0.10.36,<0.11.0)
Requires-Dist: llama-index-embeddings-huggingface (>=0.2.0,<0.3.0)
Requires-Dist: llama-index-llms-anyscale (>=0.1.4,<0.2.0)
Requires-Dist: llama-index-llms-groq (>=0.1.3,<0.2.0)
Requires-Dist: llama-index-llms-huggingface (>=0.1.5,<0.2.0)
Requires-Dist: llama-index-llms-ollama (>=0.1.3,<0.2.0)
Requires-Dist: mkdocs (>=1.6.0,<2.0.0)
Requires-Dist: mkdocs-material (>=9.5.21,<10.0.0)
Requires-Dist: mkdocstrings (>=0.25.1,<0.26.0)
Requires-Dist: mkdocstrings-python (>=1.10.0,<2.0.0)
Requires-Dist: pypdf2 (>=3.0.1,<4.0.0)
Requires-Dist: python-dotenv (>=1.0.1,<2.0.0)
Requires-Dist: spacy (>=3.7.4,<4.0.0)
Requires-Dist: streamlit (>=1.34.0,<2.0.0)
Requires-Dist: yaspin (>=3.0.2,<4.0.0)
